dukepy/__init__.py
dukepy/config.py
dukepy/converge.py
dukepy/dict_diff.py
dukepy/elastic.py
dukepy/logger.py
dukepy/mail_bot.py
dukepy/notification.py
dukepy/safe_dict.py
dukepy/shell.py
dukepy/singleton.py
dukepy/traces.py
dukepy/tray.py
dukepy/watcher.py
dukepy/flask/__init__.py
dukepy/flask/run.py
dukepy/sql_alchemy/__init__.py
dukepy/sql_alchemy/init_db.py
dukepy/sql_alchemy/app/__init__.py
dukepy/sql_alchemy/tables/__init__.py
dukepy/sql_alchemy/tables/alchemy_base.py
dukepy/sql_alchemy/tables/user.py
dukepy-1.3.0.dist-info/METADATA
dukepy-1.3.0.dist-info/WHEEL
dukepy-1.3.0.dist-info/entry_points.txt
dukepy-1.3.0.dist-info/top_level.txt
dukepy-1.3.0.dist-info/RECORD
