Metadata-Version: 2.1
Name: dukepy
Version: 1.3.0
Summary: A useful collection of utilities
Home-page: https://github.com/duke79/libpython
Author: Pulkit Singh
Author-email: pulkitsingh01@gmail.com
License: MIT License
Platform: UNKNOWN
Classifier: Programming Language :: Python :: 3
Classifier: License :: OSI Approved :: MIT License
Classifier: Operating System :: OS Independent
Requires-Dist: colorama
Requires-Dist: pypiwin32
Requires-Dist: Flask-SQLAlchemy
